{
  "source": "https://www.ccmn.cn/priceinfo/",
  "timestamp": "2026-01-24T02:35:16.281859+00:00",
  "data": [
    {
      "product": "A00铝",
      "date": "2026-01-19",
      "price": 23870.0,
      "unit": "元/吨",
      "change": -150
    },
    {
      "product": "A00铝",
      "date": "2026-01-20",
      "price": 23690.0,
      "unit": "元/吨",
      "change": -180
    },
    {
      "product": "A00铝",
      "date": "2026-01-22",
      "price": 23740.0,
      "unit": "元/吨",
      "change": 30
    },
    {
      "product": "A00铝",
      "date": "2026-01-23",
      "price": 24110.0,
      "unit": "元/吨",
      "change": 370
    },
    {
      "product": "A00铝",
      "date": "2026-12-31",
      "price": 22460.0,
      "unit": "元/吨",
      "change": 280
    }
  ]
}